{"singlePage": [], "startSite": "", "filingNum": "", "onePageListNum": 15, "commentLabelColor": "#006b75", "yearColorList": ["#bc4c00", "#0969da", "#1f883d", "#A333D0"], "i18n": "CN", "themeMode": "manual", "dayTheme": "light", "nightTheme": "dark", "urlMode": "pinyin", "script": "", "style": "", "head": "", "indexScript": "", "indexStyle": "", "bottomText": "\u8f6c\u8f7d\u8bf7\u6ce8\u660e\u51fa\u5904", "showPostSource": 1, "iconList": {}, "UTC": 8, "rssSplit": "sentence", "exlink": {}, "needComment": 1, "allHead": "<script src='https://utteranc.es/client.js'repo='jyh205/jyh205.github.io'issue-term='pathname'theme='github-light'crossorigin='anonymous'async></script>", "title": "Jyh", "subTitle": "Never Settle", "avatarUrl": "https://github.com/favicon.ico", "GMEEK_VERSION": "last", "postListJson": {}, "singeListJson": {}, "labelColorDict": {"A new start": "#4F12C9", "A \u8303": "#f9d0c4", "AI": "#300856", "AI-answer": "#fe01ed", "good first issue": "#7057ff", "\u81ea\u521b": "#62B78D", "\u8f6c\u8f7d": "#16fb36"}, "displayTitle": "Jyh", "faviconUrl": "https://github.com/favicon.ico", "ogImage": "https://github.com/favicon.ico", "primerCSS": "<link href='https://mirrors.sustech.edu.cn/cdnjs/ajax/libs/Primer/21.0.7/primer.css' rel='stylesheet' />", "homeUrl": "https://jyh205.github.io", "prevUrl": "disabled", "nextUrl": "disabled"}